[{"name":"builder","qualifiedName":"builder","href":"builder/builder-library.html","kind":9,"overriddenDepth":0,"packageRank":0,"desc":""},{"name":"application","qualifiedName":"builder.application","href":"builder/application.html","kind":8,"overriddenDepth":0,"packageRank":0,"desc":"","enclosedBy":{"name":"builder","kind":9,"href":"builder/builder-library.html"}},{"name":"controller","qualifiedName":"builder.controller","href":"builder/controller.html","kind":8,"overriddenDepth":0,"packageRank":0,"desc":"","enclosedBy":{"name":"builder","kind":9,"href":"builder/builder-library.html"}},{"name":"errorHandler","qualifiedName":"builder.errorHandler","href":"builder/errorHandler.html","kind":8,"overriddenDepth":0,"packageRank":0,"desc":"","enclosedBy":{"name":"builder","kind":9,"href":"builder/builder-library.html"}},{"name":"dartness_generator","qualifiedName":"dartness_generator","href":"dartness_generator/dartness_generator-library.html","kind":9,"overriddenDepth":0,"packageRank":0,"desc":""}]
